console_explorer/__init__.py
python_console_explorer-1.2.0.dist-info/LICENSE
python_console_explorer-1.2.0.dist-info/METADATA
python_console_explorer-1.2.0.dist-info/WHEEL
python_console_explorer-1.2.0.dist-info/top_level.txt
python_console_explorer-1.2.0.dist-info/RECORD
