Metadata-Version: 2.1
Name: python-console-explorer
Version: 1.2.0
Summary: A Python lib that enables you to load a command-line file explorer for your users !
Home-page: https://github.com/megat69/Lib_CLIExplorer
Author: megat69
License: UNKNOWN
Project-URL: Bug Tracker, https://github.com/megat69/Lib_CLIExplorer/issues
Platform: UNKNOWN
Classifier: Programming Language :: Python :: 3
Classifier: License :: OSI Approved :: GNU Affero General Public License v3
Classifier: Operating System :: OS Independent
Requires-Python: >=3.6
